setup.cfg
setup.py
vimeo_utils/__init__.py
vimeo_utils.egg-info/PKG-INFO
vimeo_utils.egg-info/SOURCES.txt
vimeo_utils.egg-info/dependency_links.txt
vimeo_utils.egg-info/top_level.txt