Metadata-Version: 1.1
Name: vimeo-utils
Version: 0.1
Summary: Vimeo-related shortcuts for Django
Home-page: https://github.com/life-in-messiah/django-vimeo-utils
Author: Joshua Austin
Author-email: joshthetechie@outlook.com
License: MIT License
Download-URL: https://github.com/life-in-messiah/django-vimeo-utils/tarball/0.1
Platform: UNKNOWN
Classifier: Environment :: Web Environment
Classifier: Framework :: Django
Classifier: Intended Audience :: Developers
Classifier: License :: OSI Approved :: MIT License
Classifier: Operating System :: OS Independent
Classifier: Programming Language :: Python
Classifier: Programming Language :: Python :: 2
Classifier: Programming Language :: Python :: 2.7
Classifier: Programming Language :: Python :: 3
Classifier: Programming Language :: Python :: 3.4
Classifier: Programming Language :: Python :: 3.5
Classifier: Topic :: Internet :: WWW/HTTP
Classifier: Topic :: Internet :: WWW/HTTP :: Dynamic Content
